{
  "experiment_id": "streaming_student_stage_loop_timingsemantic_enabled12_round1_1",
  "generated_at": "2026-03-25T21:12:06",
  "config_path": "F:/proj_dev/tmp/workdir4/configs/streaming_student_stage_template.json",
  "teacher_label_index_path": "F:/proj_dev/tmp/workdir4/data_prep/round1_1/streaming_student_teacher_labels/teacher_label_index.jsonl",
  "calibration_asset_path": "F:/proj_dev/tmp/workdir4/data_prep/round1_1/streaming_student_calibration/streaming_student_calibration_asset_estimated.json",
  "timing": {
    "started_at": "2026-03-25T21:12:03",
    "ended_at": "2026-03-25T21:12:06",
    "duration_sec": 2.962247
  },
  "split": {
    "strategy": "materialized_split",
    "split_dir": "F:/proj_dev/tmp/workdir4/data_prep/round1_1/splits/hybrid_stratified_blocked",
    "option_name": "hybrid_stratified_blocked",
    "description": "推荐方案：目标主集按时长/文本长度做均匀覆盖抽样，no_text_voice 8 条单独作为 challenge eval；源侧按时间轴做跨全局的 blocked holdout。",
    "counts": {
      "target_train": 592,
      "target_validation": 66,
      "target_special_eval": 8,
      "source_train": 483,
      "source_validation": 54
    }
  },
  "conditioning": {
    "asset_version": "stage3_calibration_asset_v1",
    "asset_status": "heuristic_bootstrap_estimated",
    "speaker_dim": 16,
    "geom_dim": 8,
    "alpha_value": 1.15,
    "source": "F:/proj_dev/tmp/workdir4/data_prep/round1_1/streaming_student_calibration/streaming_student_calibration_asset_estimated.json"
  },
  "training": {
    "batch_size": 4,
    "validation_batch_size": 4,
    "num_steps": 12,
    "validation_interval": 4,
    "checkpoint_interval": 4,
    "validation_batches": 4,
    "validation_mode": "sampled",
    "learning_rate": 0.001,
    "max_grad_norm": 1.0,
    "use_teacher_confidence": true,
    "loss_weights": {
      "teacher_z_art": 1.0,
      "teacher_event": 1.0,
      "teacher_event_prior": 0.5,
      "teacher_energy_proxy": 0.25,
      "teacher_vuv_proxy": 0.15,
      "teacher_aper_proxy": 0.1,
      "teacher_proxy_acoustic": 0.0,
      "teacher_proxy_temporal": 0.0,
      "log_f0_correction_l1": 0.01,
      "aper_correction_l1": 0.01
    },
    "semantic_supervision": {
      "enabled": true,
      "required_contract_version": "target_event_semantic_sidecar_v1",
      "required_timing_contract_version": "target_event_timing_semantic_sidecar_v1",
      "clean_text_bonus": 0.08,
      "multi_clause_bonus": 0.08,
      "multi_terminal_bonus": 0.1,
      "clause_ge4_bonus": 0.08,
      "pause_multi_bonus": 0.05,
      "terminal_present_bonus": 0.05,
      "timing_ready_bonus": 0.04,
      "timing_multi_clause_bonus": 0.04,
      "timing_pause_present_bonus": 0.03,
      "timing_terminal_present_bonus": 0.03,
      "nonverbal_penalty": 0.2,
      "event_prior_alpha": 1.0,
      "event_alpha": 0.35,
      "z_art_alpha": 0.2,
      "min_multiplier": 0.75,
      "max_multiplier": 1.45
    },
    "loss_weight_schedule": {},
    "loss_weight_overrides_path": null
  },
  "step_history": [
    {
      "step": 1,
      "started_at": "2026-03-25T21:12:05",
      "ended_at": "2026-03-25T21:12:05",
      "duration_sec": 0.11898,
      "record_ids": [
        "target::archive_firefly_1",
        "target::archive_firefly_10",
        "target::archive_firefly_11",
        "target::archive_firefly_12"
      ],
      "loss_metrics": {
        "loss_total": 23.468807,
        "loss_total_default_reference": 23.468807,
        "loss_total_semantic_disabled_reference": 20.769243,
        "loss_teacher_z_art": 9.432274,
        "loss_teacher_event": 6.557583,
        "loss_teacher_event_prior": 7.731167,
        "loss_teacher_energy_proxy": 14.01488,
        "loss_teacher_vuv_proxy": 0.703344,
        "loss_teacher_aper_proxy": 0.033752,
        "loss_teacher_proxy_acoustic": 14.213842,
        "loss_teacher_proxy_temporal": 0.006152,
        "loss_log_f0_correction_l1": 0.04628,
        "loss_aper_correction_l1": 0.030675,
        "teacher_confidence_weighted": true,
        "effective_weight_sum": 7914.069336,
        "semantic_supervision_enabled": true,
        "semantic_sidecar_present_ratio": 1.0,
        "timing_sidecar_present_ratio": 1.0,
        "semantic_weight_applied_ratio": 1.0,
        "semantic_clean_text_sample_ratio": 1.0,
        "semantic_nonverbal_sample_ratio": 0.0,
        "semantic_timing_ready_sample_ratio": 1.0,
        "semantic_timing_multi_clause_sample_ratio": 1.0,
        "semantic_timing_pause_present_sample_ratio": 1.0,
        "semantic_timing_terminal_present_sample_ratio": 0.75,
        "semantic_base_multiplier_mean": 1.4175,
        "semantic_event_prior_multiplier_mean": 1.4175,
        "semantic_event_multiplier_mean": 1.146125,
        "semantic_z_art_multiplier_mean": 1.0835
      },
      "effective_loss_weights": {
        "teacher_z_art": 1.0,
        "teacher_event": 1.0,
        "teacher_event_prior": 0.5,
        "teacher_energy_proxy": 0.25,
        "teacher_vuv_proxy": 0.15,
        "teacher_aper_proxy": 0.1,
        "teacher_proxy_acoustic": 0.0,
        "teacher_proxy_temporal": 0.0,
        "log_f0_correction_l1": 0.01,
        "aper_correction_l1": 0.01
      },
      "grad_norm": 69.100594,
      "status": "step_completed"
    },
    {
      "step": 2,
      "started_at": "2026-03-25T21:12:05",
      "ended_at": "2026-03-25T21:12:05",
      "duration_sec": 0.085019,
      "record_ids": [
        "target::archive_firefly_13",
        "target::archive_firefly_14",
        "target::archive_firefly_15",
        "target::archive_firefly_16"
      ],
      "loss_metrics": {
        "loss_total": 17.205181,
        "loss_total_default_reference": 17.205181,
        "loss_total_semantic_disabled_reference": 14.769005,
        "loss_teacher_z_art": 4.159846,
        "loss_teacher_event": 6.407213,
        "loss_teacher_event_prior": 7.867883,
        "loss_teacher_energy_proxy": 10.36085,
        "loss_teacher_vuv_proxy": 0.705324,
        "loss_teacher_aper_proxy": 0.060554,
        "loss_teacher_proxy_acoustic": 10.423652,
        "loss_teacher_proxy_temporal": 0.006344,
        "loss_log_f0_correction_l1": 0.017324,
        "loss_aper_correction_l1": 0.193989,
        "teacher_confidence_weighted": true,
        "effective_weight_sum": 8558.499023,
        "semantic_supervision_enabled": true,
        "semantic_sidecar_present_ratio": 1.0,
        "timing_sidecar_present_ratio": 1.0,
        "semantic_weight_applied_ratio": 1.0,
        "semantic_clean_text_sample_ratio": 1.0,
        "semantic_nonverbal_sample_ratio": 0.0,
        "semantic_timing_ready_sample_ratio": 1.0,
        "semantic_timing_multi_clause_sample_ratio": 1.0,
        "semantic_timing_pause_present_sample_ratio": 1.0,
        "semantic_timing_terminal_present_sample_ratio": 1.0,
        "semantic_base_multiplier_mean": 1.45,
        "semantic_event_prior_multiplier_mean": 1.45,
        "semantic_event_multiplier_mean": 1.1575,
        "semantic_z_art_multiplier_mean": 1.09
      },
      "effective_loss_weights": {
        "teacher_z_art": 1.0,
        "teacher_event": 1.0,
        "teacher_event_prior": 0.5,
        "teacher_energy_proxy": 0.25,
        "teacher_vuv_proxy": 0.15,
        "teacher_aper_proxy": 0.1,
        "teacher_proxy_acoustic": 0.0,
        "teacher_proxy_temporal": 0.0,
        "log_f0_correction_l1": 0.01,
        "aper_correction_l1": 0.01
      },
      "grad_norm": 38.820576,
      "status": "step_completed"
    },
    {
      "step": 3,
      "started_at": "2026-03-25T21:12:05",
      "ended_at": "2026-03-25T21:12:05",
      "duration_sec": 0.077536,
      "record_ids": [
        "target::archive_firefly_17",
        "target::archive_firefly_18",
        "target::archive_firefly_19",
        "target::archive_firefly_20"
      ],
      "loss_metrics": {
        "loss_total": 14.492981,
        "loss_total_default_reference": 14.492981,
        "loss_total_semantic_disabled_reference": 12.261314,
        "loss_teacher_z_art": 2.036355,
        "loss_teacher_event": 6.289993,
        "loss_teacher_event_prior": 7.78264,
        "loss_teacher_energy_proxy": 8.614946,
        "loss_teacher_vuv_proxy": 0.714665,
        "loss_teacher_aper_proxy": 0.117004,
        "loss_teacher_proxy_acoustic": 8.643545,
        "loss_teacher_proxy_temporal": 0.006568,
        "loss_log_f0_correction_l1": 0.051997,
        "loss_aper_correction_l1": 0.215458,
        "teacher_confidence_weighted": true,
        "effective_weight_sum": 8186.825195,
        "semantic_supervision_enabled": true,
        "semantic_sidecar_present_ratio": 1.0,
        "timing_sidecar_present_ratio": 1.0,
        "semantic_weight_applied_ratio": 1.0,
        "semantic_clean_text_sample_ratio": 1.0,
        "semantic_nonverbal_sample_ratio": 0.0,
        "semantic_timing_ready_sample_ratio": 1.0,
        "semantic_timing_multi_clause_sample_ratio": 1.0,
        "semantic_timing_pause_present_sample_ratio": 1.0,
        "semantic_timing_terminal_present_sample_ratio": 1.0,
        "semantic_base_multiplier_mean": 1.45,
        "semantic_event_prior_multiplier_mean": 1.45,
        "semantic_event_multiplier_mean": 1.1575,
        "semantic_z_art_multiplier_mean": 1.09
      },
      "effective_loss_weights": {
        "teacher_z_art": 1.0,
        "teacher_event": 1.0,
        "teacher_event_prior": 0.5,
        "teacher_energy_proxy": 0.25,
        "teacher_vuv_proxy": 0.15,
        "teacher_aper_proxy": 0.1,
        "teacher_proxy_acoustic": 0.0,
        "teacher_proxy_temporal": 0.0,
        "log_f0_correction_l1": 0.01,
        "aper_correction_l1": 0.01
      },
      "grad_norm": 23.79394,
      "status": "step_completed"
    },
    {
      "step": 4,
      "started_at": "2026-03-25T21:12:05",
      "ended_at": "2026-03-25T21:12:06",
      "duration_sec": 0.095348,
      "record_ids": [
        "target::archive_firefly_3",
        "target::archive_firefly_4",
        "target::archive_firefly_5",
        "target::archive_firefly_6"
      ],
      "loss_metrics": {
        "loss_total": 13.167313,
        "loss_total_default_reference": 13.167313,
        "loss_total_semantic_disabled_reference": 11.172796,
        "loss_teacher_z_art": 0.932541,
        "loss_teacher_event": 6.142259,
        "loss_teacher_event_prior": 7.55206,
        "loss_teacher_energy_proxy": 8.754843,
        "loss_teacher_vuv_proxy": 0.714681,
        "loss_teacher_aper_proxy": 0.174077,
        "loss_teacher_proxy_acoustic": 8.775471,
        "loss_teacher_proxy_temporal": 0.005666,
        "loss_log_f0_correction_l1": 0.145998,
        "loss_aper_correction_l1": 0.170092,
        "teacher_confidence_weighted": true,
        "effective_weight_sum": 7891.651367,
        "semantic_supervision_enabled": true,
        "semantic_sidecar_present_ratio": 1.0,
        "timing_sidecar_present_ratio": 1.0,
        "semantic_weight_applied_ratio": 1.0,
        "semantic_clean_text_sample_ratio": 1.0,
        "semantic_nonverbal_sample_ratio": 0.0,
        "semantic_timing_ready_sample_ratio": 1.0,
        "semantic_timing_multi_clause_sample_ratio": 1.0,
        "semantic_timing_pause_present_sample_ratio": 1.0,
        "semantic_timing_terminal_present_sample_ratio": 1.0,
        "semantic_base_multiplier_mean": 1.425,
        "semantic_event_prior_multiplier_mean": 1.425,
        "semantic_event_multiplier_mean": 1.14875,
        "semantic_z_art_multiplier_mean": 1.085
      },
      "effective_loss_weights": {
        "teacher_z_art": 1.0,
        "teacher_event": 1.0,
        "teacher_event_prior": 0.5,
        "teacher_energy_proxy": 0.25,
        "teacher_vuv_proxy": 0.15,
        "teacher_aper_proxy": 0.1,
        "teacher_proxy_acoustic": 0.0,
        "teacher_proxy_temporal": 0.0,
        "log_f0_correction_l1": 0.01,
        "aper_correction_l1": 0.01
      },
      "grad_norm": 14.294423,
      "status": "step_completed"
    },
    {
      "step": 5,
      "started_at": "2026-03-25T21:12:06",
      "ended_at": "2026-03-25T21:12:06",
      "duration_sec": 0.085056,
      "record_ids": [
        "target::archive_firefly_7",
        "target::archive_firefly_8",
        "target::archive_firefly_9",
        "target::chapter3_17_firefly_101"
      ],
      "loss_metrics": {
        "loss_total": 11.853868,
        "loss_total_default_reference": 11.853868,
        "loss_total_semantic_disabled_reference": 9.929882,
        "loss_teacher_z_art": 0.563404,
        "loss_teacher_event": 5.998243,
        "loss_teacher_event_prior": 7.393989,
        "loss_teacher_energy_proxy": 5.853965,
        "loss_teacher_vuv_proxy": 0.714829,
        "loss_teacher_aper_proxy": 0.211347,
        "loss_teacher_proxy_acoustic": 5.870505,
        "loss_teacher_proxy_temporal": 0.006555,
        "loss_log_f0_correction_l1": 0.239255,
        "loss_aper_correction_l1": 0.098349,
        "teacher_confidence_weighted": true,
        "effective_weight_sum": 7148.32959,
        "semantic_supervision_enabled": true,
        "semantic_sidecar_present_ratio": 1.0,
        "timing_sidecar_present_ratio": 1.0,
        "semantic_weight_applied_ratio": 1.0,
        "semantic_clean_text_sample_ratio": 1.0,
        "semantic_nonverbal_sample_ratio": 0.0,
        "semantic_timing_ready_sample_ratio": 1.0,
        "semantic_timing_multi_clause_sample_ratio": 1.0,
        "semantic_timing_pause_present_sample_ratio": 1.0,
        "semantic_timing_terminal_present_sample_ratio": 1.0,
        "semantic_base_multiplier_mean": 1.425,
        "semantic_event_prior_multiplier_mean": 1.425,
        "semantic_event_multiplier_mean": 1.14875,
        "semantic_z_art_multiplier_mean": 1.085
      },
      "effective_loss_weights": {
        "teacher_z_art": 1.0,
        "teacher_event": 1.0,
        "teacher_event_prior": 0.5,
        "teacher_energy_proxy": 0.25,
        "teacher_vuv_proxy": 0.15,
        "teacher_aper_proxy": 0.1,
        "teacher_proxy_acoustic": 0.0,
        "teacher_proxy_temporal": 0.0,
        "log_f0_correction_l1": 0.01,
        "aper_correction_l1": 0.01
      },
      "grad_norm": 8.081041,
      "status": "step_completed"
    },
    {
      "step": 6,
      "started_at": "2026-03-25T21:12:06",
      "ended_at": "2026-03-25T21:12:06",
      "duration_sec": 0.048353,
      "record_ids": [
        "target::chapter3_17_firefly_102",
        "target::chapter3_17_firefly_103",
        "target::chapter3_17_firefly_104",
        "target::chapter3_17_firefly_105"
      ],
      "loss_metrics": {
        "loss_total": 10.458236,
        "loss_total_default_reference": 10.458236,
        "loss_total_semantic_disabled_reference": 8.977248,
        "loss_teacher_z_art": 0.438176,
        "loss_teacher_event": 5.663021,
        "loss_teacher_event_prior": 6.752111,
        "loss_teacher_energy_proxy": 3.405439,
        "loss_teacher_vuv_proxy": 0.711819,
        "loss_teacher_aper_proxy": 0.198201,
        "loss_teacher_proxy_acoustic": 3.421135,
        "loss_teacher_proxy_temporal": 0.007577,
        "loss_log_f0_correction_l1": 0.291817,
        "loss_aper_correction_l1": 0.01105,
        "teacher_confidence_weighted": true,
        "effective_weight_sum": 1438.592896,
        "semantic_supervision_enabled": true,
        "semantic_sidecar_present_ratio": 1.0,
        "timing_sidecar_present_ratio": 1.0,
        "semantic_weight_applied_ratio": 1.0,
        "semantic_clean_text_sample_ratio": 1.0,
        "semantic_nonverbal_sample_ratio": 0.0,
        "semantic_timing_ready_sample_ratio": 1.0,
        "semantic_timing_multi_clause_sample_ratio": 0.75,
        "semantic_timing_pause_present_sample_ratio": 0.75,
        "semantic_timing_terminal_present_sample_ratio": 1.0,
        "semantic_base_multiplier_mean": 1.3375,
        "semantic_event_prior_multiplier_mean": 1.3375,
        "semantic_event_multiplier_mean": 1.118125,
        "semantic_z_art_multiplier_mean": 1.0675
      },
      "effective_loss_weights": {
        "teacher_z_art": 1.0,
        "teacher_event": 1.0,
        "teacher_event_prior": 0.5,
        "teacher_energy_proxy": 0.25,
        "teacher_vuv_proxy": 0.15,
        "teacher_aper_proxy": 0.1,
        "teacher_proxy_acoustic": 0.0,
        "teacher_proxy_temporal": 0.0,
        "log_f0_correction_l1": 0.01,
        "aper_correction_l1": 0.01
      },
      "grad_norm": 7.626226,
      "status": "step_completed"
    },
    {
      "step": 7,
      "started_at": "2026-03-25T21:12:06",
      "ended_at": "2026-03-25T21:12:06",
      "duration_sec": 0.043774,
      "record_ids": [
        "target::chapter3_17_firefly_107",
        "target::chapter3_17_firefly_108",
        "target::chapter3_17_firefly_109",
        "target::chapter3_17_firefly_110"
      ],
      "loss_metrics": {
        "loss_total": 10.171884,
        "loss_total_default_reference": 10.171884,
        "loss_total_semantic_disabled_reference": 8.752181,
        "loss_teacher_z_art": 0.391588,
        "loss_teacher_event": 5.559831,
        "loss_teacher_event_prior": 6.582445,
        "loss_teacher_energy_proxy": 3.230009,
        "loss_teacher_vuv_proxy": 0.706601,
        "loss_teacher_aper_proxy": 0.123606,
        "loss_teacher_proxy_acoustic": 3.246478,
        "loss_teacher_proxy_temporal": 0.00756,
        "loss_log_f0_correction_l1": 0.277998,
        "loss_aper_correction_l1": 0.060963,
        "teacher_confidence_weighted": true,
        "effective_weight_sum": 1970.298096,
        "semantic_supervision_enabled": true,
        "semantic_sidecar_present_ratio": 1.0,
        "timing_sidecar_present_ratio": 1.0,
        "semantic_weight_applied_ratio": 1.0,
        "semantic_clean_text_sample_ratio": 1.0,
        "semantic_nonverbal_sample_ratio": 0.0,
        "semantic_timing_ready_sample_ratio": 1.0,
        "semantic_timing_multi_clause_sample_ratio": 0.75,
        "semantic_timing_pause_present_sample_ratio": 0.75,
        "semantic_timing_terminal_present_sample_ratio": 1.0,
        "semantic_base_multiplier_mean": 1.33,
        "semantic_event_prior_multiplier_mean": 1.33,
        "semantic_event_multiplier_mean": 1.1155,
        "semantic_z_art_multiplier_mean": 1.066
      },
      "effective_loss_weights": {
        "teacher_z_art": 1.0,
        "teacher_event": 1.0,
        "teacher_event_prior": 0.5,
        "teacher_energy_proxy": 0.25,
        "teacher_vuv_proxy": 0.15,
        "teacher_aper_proxy": 0.1,
        "teacher_proxy_acoustic": 0.0,
        "teacher_proxy_temporal": 0.0,
        "log_f0_correction_l1": 0.01,
        "aper_correction_l1": 0.01
      },
      "grad_norm": 7.109347,
      "status": "step_completed"
    },
    {
      "step": 8,
      "started_at": "2026-03-25T21:12:06",
      "ended_at": "2026-03-25T21:12:06",
      "duration_sec": 0.067439,
      "record_ids": [
        "target::chapter3_17_firefly_111",
        "target::chapter3_17_firefly_113",
        "target::chapter3_17_firefly_114",
        "target::chapter3_17_firefly_115"
      ],
      "loss_metrics": {
        "loss_total": 10.26898,
        "loss_total_default_reference": 10.26898,
        "loss_total_semantic_disabled_reference": 8.90909,
        "loss_teacher_z_art": 0.435147,
        "loss_teacher_event": 5.548838,
        "loss_teacher_event_prior": 6.480942,
        "loss_teacher_energy_proxy": 3.718203,
        "loss_teacher_vuv_proxy": 0.709504,
        "loss_teacher_aper_proxy": 0.052575,
        "loss_teacher_proxy_acoustic": 3.735526,
        "loss_teacher_proxy_temporal": 0.005572,
        "loss_log_f0_correction_l1": 0.246291,
        "loss_aper_correction_l1": 0.082901,
        "teacher_confidence_weighted": true,
        "effective_weight_sum": 1828.249023,
        "semantic_supervision_enabled": true,
        "semantic_sidecar_present_ratio": 1.0,
        "timing_sidecar_present_ratio": 1.0,
        "semantic_weight_applied_ratio": 1.0,
        "semantic_clean_text_sample_ratio": 1.0,
        "semantic_nonverbal_sample_ratio": 0.0,
        "semantic_timing_ready_sample_ratio": 1.0,
        "semantic_timing_multi_clause_sample_ratio": 0.75,
        "semantic_timing_pause_present_sample_ratio": 0.75,
        "semantic_timing_terminal_present_sample_ratio": 1.0,
        "semantic_base_multiplier_mean": 1.3175,
        "semantic_event_prior_multiplier_mean": 1.3175,
        "semantic_event_multiplier_mean": 1.111125,
        "semantic_z_art_multiplier_mean": 1.0635
      },
      "effective_loss_weights": {
        "teacher_z_art": 1.0,
        "teacher_event": 1.0,
        "teacher_event_prior": 0.5,
        "teacher_energy_proxy": 0.25,
        "teacher_vuv_proxy": 0.15,
        "teacher_aper_proxy": 0.1,
        "teacher_proxy_acoustic": 0.0,
        "teacher_proxy_temporal": 0.0,
        "log_f0_correction_l1": 0.01,
        "aper_correction_l1": 0.01
      },
      "grad_norm": 7.943699,
      "status": "step_completed"
    },
    {
      "step": 9,
      "started_at": "2026-03-25T21:12:06",
      "ended_at": "2026-03-25T21:12:06",
      "duration_sec": 0.075075,
      "record_ids": [
        "target::chapter3_17_firefly_116",
        "target::chapter3_17_firefly_117",
        "target::chapter3_17_firefly_118",
        "target::chapter3_17_firefly_120"
      ],
      "loss_metrics": {
        "loss_total": 10.524556,
        "loss_total_default_reference": 10.524556,
        "loss_total_semantic_disabled_reference": 8.72757,
        "loss_teacher_z_art": 0.308578,
        "loss_teacher_event": 5.688014,
        "loss_teacher_event_prior": 6.942731,
        "loss_teacher_energy_proxy": 3.781075,
        "loss_teacher_vuv_proxy": 0.71022,
        "loss_teacher_aper_proxy": 0.015638,
        "loss_teacher_proxy_acoustic": 3.799665,
        "loss_teacher_proxy_temporal": 0.005112,
        "loss_log_f0_correction_l1": 0.215045,
        "loss_aper_correction_l1": 0.108322,
        "teacher_confidence_weighted": true,
        "effective_weight_sum": 5072.322266,
        "semantic_supervision_enabled": true,
        "semantic_sidecar_present_ratio": 1.0,
        "timing_sidecar_present_ratio": 1.0,
        "semantic_weight_applied_ratio": 1.0,
        "semantic_clean_text_sample_ratio": 1.0,
        "semantic_nonverbal_sample_ratio": 0.0,
        "semantic_timing_ready_sample_ratio": 1.0,
        "semantic_timing_multi_clause_sample_ratio": 1.0,
        "semantic_timing_pause_present_sample_ratio": 1.0,
        "semantic_timing_terminal_present_sample_ratio": 1.0,
        "semantic_base_multiplier_mean": 1.425,
        "semantic_event_prior_multiplier_mean": 1.425,
        "semantic_event_multiplier_mean": 1.14875,
        "semantic_z_art_multiplier_mean": 1.085
      },
      "effective_loss_weights": {
        "teacher_z_art": 1.0,
        "teacher_event": 1.0,
        "teacher_event_prior": 0.5,
        "teacher_energy_proxy": 0.25,
        "teacher_vuv_proxy": 0.15,
        "teacher_aper_proxy": 0.1,
        "teacher_proxy_acoustic": 0.0,
        "teacher_proxy_temporal": 0.0,
        "log_f0_correction_l1": 0.01,
        "aper_correction_l1": 0.01
      },
      "grad_norm": 5.649839,
      "status": "step_completed"
    },
    {
      "step": 10,
      "started_at": "2026-03-25T21:12:06",
      "ended_at": "2026-03-25T21:12:06",
      "duration_sec": 0.056166,
      "record_ids": [
        "target::chapter3_17_firefly_121",
        "target::chapter3_17_firefly_122",
        "target::chapter3_17_firefly_123",
        "target::chapter3_17_firefly_124"
      ],
      "loss_metrics": {
        "loss_total": 9.850322,
        "loss_total_default_reference": 9.850322,
        "loss_total_semantic_disabled_reference": 8.388364,
        "loss_teacher_z_art": 0.216875,
        "loss_teacher_event": 5.551961,
        "loss_teacher_event_prior": 6.58382,
        "loss_teacher_energy_proxy": 2.717529,
        "loss_teacher_vuv_proxy": 0.711628,
        "loss_teacher_aper_proxy": 0.005757,
        "loss_teacher_proxy_acoustic": 2.737746,
        "loss_teacher_proxy_temporal": 0.005225,
        "loss_log_f0_correction_l1": 0.15815,
        "loss_aper_correction_l1": 0.129157,
        "teacher_confidence_weighted": true,
        "effective_weight_sum": 3255.075195,
        "semantic_supervision_enabled": true,
        "semantic_sidecar_present_ratio": 1.0,
        "timing_sidecar_present_ratio": 1.0,
        "semantic_weight_applied_ratio": 1.0,
        "semantic_clean_text_sample_ratio": 1.0,
        "semantic_nonverbal_sample_ratio": 0.0,
        "semantic_timing_ready_sample_ratio": 1.0,
        "semantic_timing_multi_clause_sample_ratio": 1.0,
        "semantic_timing_pause_present_sample_ratio": 1.0,
        "semantic_timing_terminal_present_sample_ratio": 0.75,
        "semantic_base_multiplier_mean": 1.3475,
        "semantic_event_prior_multiplier_mean": 1.3475,
        "semantic_event_multiplier_mean": 1.121625,
        "semantic_z_art_multiplier_mean": 1.0695
      },
      "effective_loss_weights": {
        "teacher_z_art": 1.0,
        "teacher_event": 1.0,
        "teacher_event_prior": 0.5,
        "teacher_energy_proxy": 0.25,
        "teacher_vuv_proxy": 0.15,
        "teacher_aper_proxy": 0.1,
        "teacher_proxy_acoustic": 0.0,
        "teacher_proxy_temporal": 0.0,
        "log_f0_correction_l1": 0.01,
        "aper_correction_l1": 0.01
      },
      "grad_norm": 6.212742,
      "status": "step_completed"
    },
    {
      "step": 11,
      "started_at": "2026-03-25T21:12:06",
      "ended_at": "2026-03-25T21:12:06",
      "duration_sec": 0.066948,
      "record_ids": [
        "target::chapter3_17_firefly_125",
        "target::chapter3_17_firefly_126",
        "target::chapter3_17_firefly_127",
        "target::chapter3_17_firefly_128"
      ],
      "loss_metrics": {
        "loss_total": 9.97675,
        "loss_total_default_reference": 9.97675,
        "loss_total_semantic_disabled_reference": 8.208875,
        "loss_teacher_z_art": 0.190449,
        "loss_teacher_event": 5.601357,
        "loss_teacher_event_prior": 6.887564,
        "loss_teacher_energy_proxy": 2.522042,
        "loss_teacher_vuv_proxy": 0.708001,
        "loss_teacher_aper_proxy": 0.022414,
        "loss_teacher_proxy_acoustic": 2.543867,
        "loss_teacher_proxy_temporal": 0.005236,
        "loss_log_f0_correction_l1": 0.089686,
        "loss_aper_correction_l1": 0.131427,
        "teacher_confidence_weighted": true,
        "effective_weight_sum": 5477.573242,
        "semantic_supervision_enabled": true,
        "semantic_sidecar_present_ratio": 1.0,
        "timing_sidecar_present_ratio": 1.0,
        "semantic_weight_applied_ratio": 1.0,
        "semantic_clean_text_sample_ratio": 1.0,
        "semantic_nonverbal_sample_ratio": 0.0,
        "semantic_timing_ready_sample_ratio": 1.0,
        "semantic_timing_multi_clause_sample_ratio": 1.0,
        "semantic_timing_pause_present_sample_ratio": 1.0,
        "semantic_timing_terminal_present_sample_ratio": 1.0,
        "semantic_base_multiplier_mean": 1.425,
        "semantic_event_prior_multiplier_mean": 1.425,
        "semantic_event_multiplier_mean": 1.14875,
        "semantic_z_art_multiplier_mean": 1.085
      },
      "effective_loss_weights": {
        "teacher_z_art": 1.0,
        "teacher_event": 1.0,
        "teacher_event_prior": 0.5,
        "teacher_energy_proxy": 0.25,
        "teacher_vuv_proxy": 0.15,
        "teacher_aper_proxy": 0.1,
        "teacher_proxy_acoustic": 0.0,
        "teacher_proxy_temporal": 0.0,
        "log_f0_correction_l1": 0.01,
        "aper_correction_l1": 0.01
      },
      "grad_norm": 6.690558,
      "status": "step_completed"
    },
    {
      "step": 12,
      "started_at": "2026-03-25T21:12:06",
      "ended_at": "2026-03-25T21:12:06",
      "duration_sec": 0.06617,
      "record_ids": [
        "target::chapter3_17_firefly_130",
        "target::chapter3_17_firefly_131",
        "target::chapter3_17_firefly_132",
        "target::chapter3_17_firefly_134"
      ],
      "loss_metrics": {
        "loss_total": 9.640078,
        "loss_total_default_reference": 9.640078,
        "loss_total_semantic_disabled_reference": 8.087667,
        "loss_teacher_z_art": 0.150239,
        "loss_teacher_event": 5.483273,
        "loss_teacher_event_prior": 6.630949,
        "loss_teacher_energy_proxy": 2.308064,
        "loss_teacher_vuv_proxy": 0.710389,
        "loss_teacher_aper_proxy": 0.054178,
        "loss_teacher_proxy_acoustic": 2.333601,
        "loss_teacher_proxy_temporal": 0.004991,
        "loss_log_f0_correction_l1": 0.100163,
        "loss_aper_correction_l1": 0.109742,
        "teacher_confidence_weighted": true,
        "effective_weight_sum": 4668.414062,
        "semantic_supervision_enabled": true,
        "semantic_sidecar_present_ratio": 1.0,
        "timing_sidecar_present_ratio": 1.0,
        "semantic_weight_applied_ratio": 1.0,
        "semantic_clean_text_sample_ratio": 1.0,
        "semantic_nonverbal_sample_ratio": 0.0,
        "semantic_timing_ready_sample_ratio": 1.0,
        "semantic_timing_multi_clause_sample_ratio": 0.75,
        "semantic_timing_pause_present_sample_ratio": 0.75,
        "semantic_timing_terminal_present_sample_ratio": 1.0,
        "semantic_base_multiplier_mean": 1.375,
        "semantic_event_prior_multiplier_mean": 1.375,
        "semantic_event_multiplier_mean": 1.13125,
        "semantic_z_art_multiplier_mean": 1.075
      },
      "effective_loss_weights": {
        "teacher_z_art": 1.0,
        "teacher_event": 1.0,
        "teacher_event_prior": 0.5,
        "teacher_energy_proxy": 0.25,
        "teacher_vuv_proxy": 0.15,
        "teacher_aper_proxy": 0.1,
        "teacher_proxy_acoustic": 0.0,
        "teacher_proxy_temporal": 0.0,
        "log_f0_correction_l1": 0.01,
        "aper_correction_l1": 0.01
      },
      "grad_norm": 7.616419,
      "status": "step_completed"
    }
  ],
  "validation_history": [
    {
      "step": 4,
      "validation_mode": "sampled",
      "validation_batches": 4,
      "record_count": 66,
      "effective_loss_weights": {
        "teacher_z_art": 1.0,
        "teacher_event": 1.0,
        "teacher_event_prior": 0.5,
        "teacher_energy_proxy": 0.25,
        "teacher_vuv_proxy": 0.15,
        "teacher_aper_proxy": 0.1,
        "teacher_proxy_acoustic": 0.0,
        "teacher_proxy_temporal": 0.0,
        "log_f0_correction_l1": 0.01,
        "aper_correction_l1": 0.01
      },
      "sampled_record_ids": [
        [
          "target::chapter3_3_firefly_197",
          "target::chapter3_29_firefly_103",
          "target::chapter3_30_firefly_137",
          "target::chapter3_3_firefly_212"
        ],
        [
          "target::chapter3_4_firefly_109",
          "target::chapter3_26_firefly_107",
          "target::chapter3_29_firefly_142",
          "target::chapter3_3_firefly_215"
        ],
        [
          "target::chapter3_3_firefly_210",
          "target::chapter3_29_firefly_136",
          "target::chapter3_4_firefly_105",
          "target::chapter3_17_firefly_133"
        ],
        [
          "target::chapter3_2_firefly_157",
          "target::chapter3_2_firefly_178",
          "target::chapter4_7_firefly_119",
          "target::chapter3_17_firefly_129"
        ]
      ],
      "loss_metrics": {
        "loss_total": 12.004342,
        "loss_total_default_reference": 12.004342,
        "loss_total_semantic_disabled_reference": 10.011284,
        "loss_teacher_z_art": 0.58326,
        "loss_teacher_event": 6.016978,
        "loss_teacher_event_prior": 7.466024,
        "loss_teacher_energy_proxy": 6.156545,
        "loss_teacher_vuv_proxy": 0.715373,
        "loss_teacher_aper_proxy": 0.212578,
        "loss_teacher_proxy_acoustic": 6.172942,
        "loss_teacher_proxy_temporal": 0.005182,
        "loss_log_f0_correction_l1": 0.240307,
        "loss_aper_correction_l1": 0.098875,
        "teacher_confidence_weighted": true,
        "effective_weight_sum": 5916.146973,
        "semantic_supervision_enabled": true,
        "semantic_sidecar_present_ratio": 1.0,
        "timing_sidecar_present_ratio": 1.0,
        "semantic_weight_applied_ratio": 1.0,
        "semantic_clean_text_sample_ratio": 1.0,
        "semantic_nonverbal_sample_ratio": 0.0,
        "semantic_timing_ready_sample_ratio": 1.0,
        "semantic_timing_multi_clause_sample_ratio": 1.0,
        "semantic_timing_pause_present_sample_ratio": 1.0,
        "semantic_timing_terminal_present_sample_ratio": 1.0,
        "semantic_base_multiplier_mean": 1.440625,
        "semantic_event_prior_multiplier_mean": 1.440625,
        "semantic_event_multiplier_mean": 1.154219,
        "semantic_z_art_multiplier_mean": 1.088125
      }
    },
    {
      "step": 8,
      "validation_mode": "sampled",
      "validation_batches": 4,
      "record_count": 66,
      "effective_loss_weights": {
        "teacher_z_art": 1.0,
        "teacher_event": 1.0,
        "teacher_event_prior": 0.5,
        "teacher_energy_proxy": 0.25,
        "teacher_vuv_proxy": 0.15,
        "teacher_aper_proxy": 0.1,
        "teacher_proxy_acoustic": 0.0,
        "teacher_proxy_temporal": 0.0,
        "log_f0_correction_l1": 0.01,
        "aper_correction_l1": 0.01
      },
      "sampled_record_ids": [
        [
          "target::chapter4_7_firefly_105",
          "target::chapter3_3_firefly_245",
          "target::chapter3_3_firefly_197",
          "target::chapter3_29_firefly_103"
        ],
        [
          "target::chapter3_30_firefly_137",
          "target::chapter3_3_firefly_212",
          "target::chapter3_4_firefly_109",
          "target::chapter3_26_firefly_107"
        ],
        [
          "target::chapter3_29_firefly_142",
          "target::chapter3_3_firefly_215",
          "target::chapter3_3_firefly_210",
          "target::chapter3_29_firefly_136"
        ],
        [
          "target::chapter3_4_firefly_105",
          "target::chapter3_17_firefly_133",
          "target::chapter3_2_firefly_157",
          "target::chapter3_2_firefly_178"
        ]
      ],
      "loss_metrics": {
        "loss_total": 10.814014,
        "loss_total_default_reference": 10.814014,
        "loss_total_semantic_disabled_reference": 8.949388,
        "loss_teacher_z_art": 0.33009,
        "loss_teacher_event": 5.718971,
        "loss_teacher_event_prior": 7.020707,
        "loss_teacher_energy_proxy": 4.573644,
        "loss_teacher_vuv_proxy": 0.709,
        "loss_teacher_aper_proxy": 0.015946,
        "loss_teacher_proxy_acoustic": 4.592161,
        "loss_teacher_proxy_temporal": 0.004423,
        "loss_log_f0_correction_l1": 0.218894,
        "loss_aper_correction_l1": 0.105358,
        "teacher_confidence_weighted": true,
        "effective_weight_sum": 5394.04956,
        "semantic_supervision_enabled": true,
        "semantic_sidecar_present_ratio": 1.0,
        "timing_sidecar_present_ratio": 1.0,
        "semantic_weight_applied_ratio": 1.0,
        "semantic_clean_text_sample_ratio": 1.0,
        "semantic_nonverbal_sample_ratio": 0.0,
        "semantic_timing_ready_sample_ratio": 1.0,
        "semantic_timing_multi_clause_sample_ratio": 1.0,
        "semantic_timing_pause_present_sample_ratio": 1.0,
        "semantic_timing_terminal_present_sample_ratio": 1.0,
        "semantic_base_multiplier_mean": 1.440625,
        "semantic_event_prior_multiplier_mean": 1.440625,
        "semantic_event_multiplier_mean": 1.154219,
        "semantic_z_art_multiplier_mean": 1.088125
      }
    },
    {
      "step": 12,
      "validation_mode": "sampled",
      "validation_batches": 4,
      "record_count": 66,
      "effective_loss_weights": {
        "teacher_z_art": 1.0,
        "teacher_event": 1.0,
        "teacher_event_prior": 0.5,
        "teacher_energy_proxy": 0.25,
        "teacher_vuv_proxy": 0.15,
        "teacher_aper_proxy": 0.1,
        "teacher_proxy_acoustic": 0.0,
        "teacher_proxy_temporal": 0.0,
        "log_f0_correction_l1": 0.01,
        "aper_correction_l1": 0.01
      },
      "sampled_record_ids": [
        [
          "target::chapter3_4_firefly_112",
          "target::chapter3_30_firefly_136",
          "target::chapter4_7_firefly_105",
          "target::chapter3_3_firefly_245"
        ],
        [
          "target::chapter3_3_firefly_197",
          "target::chapter3_29_firefly_103",
          "target::chapter3_30_firefly_137",
          "target::chapter3_3_firefly_212"
        ],
        [
          "target::chapter3_4_firefly_109",
          "target::chapter3_26_firefly_107",
          "target::chapter3_29_firefly_142",
          "target::chapter3_3_firefly_215"
        ],
        [
          "target::chapter3_3_firefly_210",
          "target::chapter3_29_firefly_136",
          "target::chapter3_4_firefly_105",
          "target::chapter3_17_firefly_133"
        ]
      ],
      "loss_metrics": {
        "loss_total": 9.94682,
        "loss_total_default_reference": 9.94682,
        "loss_total_semantic_disabled_reference": 8.181019,
        "loss_teacher_z_art": 0.082807,
        "loss_teacher_event": 5.572083,
        "loss_teacher_event_prior": 6.900272,
        "loss_teacher_energy_proxy": 2.899665,
        "loss_teacher_vuv_proxy": 0.722334,
        "loss_teacher_aper_proxy": 0.064019,
        "loss_teacher_proxy_acoustic": 2.928775,
        "loss_teacher_proxy_temporal": 0.005314,
        "loss_log_f0_correction_l1": 0.136638,
        "loss_aper_correction_l1": 0.075962,
        "teacher_confidence_weighted": true,
        "effective_weight_sum": 4918.224121,
        "semantic_supervision_enabled": true,
        "semantic_sidecar_present_ratio": 1.0,
        "timing_sidecar_present_ratio": 1.0,
        "semantic_weight_applied_ratio": 1.0,
        "semantic_clean_text_sample_ratio": 1.0,
        "semantic_nonverbal_sample_ratio": 0.0,
        "semantic_timing_ready_sample_ratio": 1.0,
        "semantic_timing_multi_clause_sample_ratio": 1.0,
        "semantic_timing_pause_present_sample_ratio": 1.0,
        "semantic_timing_terminal_present_sample_ratio": 0.9375,
        "semantic_base_multiplier_mean": 1.4275,
        "semantic_event_prior_multiplier_mean": 1.4275,
        "semantic_event_multiplier_mean": 1.149625,
        "semantic_z_art_multiplier_mean": 1.0855
      }
    }
  ],
  "artifacts": {
    "checkpoint_paths": [
      "F:/proj_dev/tmp/workdir4/reports/training/streaming_student_loop_timingsemantic_enabled12_round1_1/checkpoints/streaming_student_stage_loop_timingsemantic_enabled12_round1_1.step4.pt",
      "F:/proj_dev/tmp/workdir4/reports/training/streaming_student_loop_timingsemantic_enabled12_round1_1/checkpoints/streaming_student_stage_loop_timingsemantic_enabled12_round1_1.step8.pt",
      "F:/proj_dev/tmp/workdir4/reports/training/streaming_student_loop_timingsemantic_enabled12_round1_1/checkpoints/streaming_student_stage_loop_timingsemantic_enabled12_round1_1.step12.pt"
    ],
    "latest_checkpoint_path": "F:/proj_dev/tmp/workdir4/reports/training/streaming_student_loop_timingsemantic_enabled12_round1_1/checkpoints/streaming_student_stage_loop_timingsemantic_enabled12_round1_1.step12.pt",
    "best_checkpoint": {
      "selection_rule": "min_validation_loss_total_over_recorded_checkpoints",
      "step": 12,
      "validation_mode": "sampled",
      "loss_total": 9.94682,
      "checkpoint_path": "F:/proj_dev/tmp/workdir4/reports/training/streaming_student_loop_timingsemantic_enabled12_round1_1/checkpoints/streaming_student_stage_loop_timingsemantic_enabled12_round1_1.step12.pt"
    }
  },
  "notes": [
    "This is a minimal multi-step Stage3 training loop scaffold built on top of the new teacher-supervised contract.",
    "Validation currently averages a small sampled subset of target_validation batches for speed; it is not a full-slice evaluation.",
    "The purpose is to expose step-wise loss, grad_norm, validation, and checkpoint behavior before adding richer supervision or r_res."
  ],
  "next_steps": [
    "Decide whether sampled validation should remain the default quick-check mode or whether fuller validation should become the default before larger runs.",
    "Tune learning rate, loss weights, and teacher confidence usage based on short-horizon trajectories instead of a single step.",
    "Keep hidden distillation and r_res disabled until the base multi-step route is stable."
  ],
  "status": "training_loop_scaffold_completed"
}